tensordiffeq/__init__.py
tensordiffeq/boundaries.py
tensordiffeq/domains.py
tensordiffeq/fit.py
tensordiffeq/helpers.py
tensordiffeq/models.py
tensordiffeq/networks.py
tensordiffeq/optimizers.py
tensordiffeq/output.py
tensordiffeq/plotting.py
tensordiffeq/sampling.py
tensordiffeq/utils.py
tensordiffeq-0.2.0.dist-info/METADATA
tensordiffeq-0.2.0.dist-info/WHEEL
tensordiffeq-0.2.0.dist-info/top_level.txt
tensordiffeq-0.2.0.dist-info/RECORD
